django_i18n_utils/__init__.py
django_i18n_utils/formfields.py
django_i18n_utils/models.py
django_i18n_utils/testcases.py
django_i18n_utils/testclients.py
django_i18n_utils/utils.py
django_i18n_utils/validators.py
django_i18n_utils-1.5.3.dist-info/DESCRIPTION.rst
django_i18n_utils-1.5.3.dist-info/METADATA
django_i18n_utils-1.5.3.dist-info/metadata.json
django_i18n_utils-1.5.3.dist-info/pbr.json
django_i18n_utils-1.5.3.dist-info/RECORD
django_i18n_utils-1.5.3.dist-info/top_level.txt
django_i18n_utils-1.5.3.dist-info/WHEEL
