Metadata-Version: 2.0
Name: django-i18n-utils
Version: 1.5.3
Summary: Utilities for localized Django projects
Home-page: https://pypi.python.org/pypi/django-i18n-utils
Author: Chris Adams
Author-email: chris@improbable.org
License: MIT License
Keywords: django i18n
Platform: UNKNOWN
Classifier: Development Status :: 4 - Beta
Classifier: Environment :: Web Environment
Classifier: Framework :: Django
Classifier: Intended Audience :: Developers
Classifier: License :: OSI Approved :: MIT License
Classifier: Operating System :: OS Independent
Classifier: Programming Language :: Python
Classifier: Topic :: Software Development :: Libraries :: Python Modules
Classifier: Topic :: Software Development :: Localization
